MANIFEST.in
README.rst
setup.py
sentry_redmine/__init__.py
sentry_redmine/models.py
sentry_redmine/plugin.py
sentry_redmine.egg-info/PKG-INFO
sentry_redmine.egg-info/SOURCES.txt
sentry_redmine.egg-info/dependency_links.txt
sentry_redmine.egg-info/entry_points.txt
sentry_redmine.egg-info/not-zip-safe
sentry_redmine.egg-info/requires.txt
sentry_redmine.egg-info/top_level.txt