Metadata-Version: 1.0
Name: sentry-redmine
Version: 0.1.0
Summary: A Sentry extension which integrates with Redmine.
Home-page: http://github.com/ideadevice/sentry-redmine
Author: Aaditya Sood
Author-email: a@ideadevice.com
License: BSD
Platform: UNKNOWN
Classifier: Framework :: Django
Classifier: Intended Audience :: Developers
Classifier: Intended Audience :: System Administrators
Classifier: Operating System :: OS Independent
Classifier: Topic :: Software Development
